Workbook

Sheet Explication
A1: Interet | B1: Utilisation prévision banque de France dans nos prévisions / utile pour test out-of-sample
A3: Caractéristiques | B3: Certains variables sont en taux de variation et pas en niveau
A4: Problématique | B4: Certaines variables sont prédite en valeure réel alors que nos modèles utilisent des variables à prix courant
A6: Reconstruction
A7: Etape 1 | B7: Pour le PIB nominal et la FBCF le taux est transformer pour devenir un taux a euro courant comme tel : g_courant = ((1+g_reel/100)*(1+deflateur_du_pib/100) -1) / 100 | Approximation pour variation FBCF
A8: ETAPE 2 | B8: On applique le taux de variation a nos variable pour les avoir en niveau
A10: Approximation | B10: La variation des salaires négocié et approximé par la variation des salaires brut

Sheet Prev_j_2015
A1: time | B1: PIB_variation | C1: taux_epargne | D1: chomage | E1: EURIBOR | F1: Taux_long | G1: FBCF_variation | H1: RDB_variation | I1: salaires_brut | J1: N_PIB_réel | K1: N_FBCF_réel | L1: N_Déflateur
A2: 2015 | B2: =((1+J2/100) * (1+L2/100) -1) * 100 -> 2.212 | C2: 15.1 | D2: 10.3 | E2: 0 | F2: 0.9 | G2: =((1+K2/100) * (1+L2/100) -1) * 100 -> 2.111 | H2: 1.7 | I2: 0.9 | J2: 1.2 | K2: 1.1 | L2: 1
A3: 2016 | B3: =((1+J3/100) * (1+L3/100) -1) * 100 -> 2.818 | C3: 14.9 | D3: 10.1 | E3: 0 | F3: 1.2 | G3: =((1+K3/100) * (1+L3/100) -1) * 100 -> 5.444 | H3: 2.6 | I3: 1.4 | J3: 1.8 | K3: 4.4 | L3: 1
A4: 2017 | B4: =((1+J4/100) * (1+L4/100) -1) * 100 -> 3.1228 | C4: 14.9 | D4: 9.6 | E4: 0.2 | F4: 1.5 | G4: =((1+K4/100) * (1+L4/100) -1) * 100 -> 5.4504 | H4: 3.1 | I4: 1.8 | J4: 1.9 | K4: 4.2 | L4: 1.2

Sheet Prev_d_2015
A1: time | B1: PIB_variation | C1: taux_epargne | D1: chomage | E1: EURIBOR | F1: Taux_long | G1: FBCF_variation | H1: RDB_variation | I1: salaires_brut | J1: N_PIB_réel | K1: N_FBCF_réel | L1: N_Déflateur
A2: 2015 | B2: =((1+J2/100) * (1+L2/100) -1) * 100 -> 2.5156 | C2: 15.2 | D2: 10.2 | E2: -0.02 | F2: 0.9 | G2: =((1+K2/100) * (1+L2/100) -1) * 100 -> 3.2247 | H2: 1.7 | I2: 1.1 | J2: 1.2 | K2: 1.9 | L2: 1.3
A3: 2016 | B3: =((1+J3/100) * (1+L3/100) -1) * 100 -> 2.5154 | C3: 15 | D3: 10 | E3: -0.19 | F3: 1.1 | G3: =((1+K3/100) * (1+L3/100) -1) * 100 -> 4.5374 | H3: 2.1 | I3: 1.2 | J3: 1.4 | K3: 3.4 | L3: 1.1
A4: 2017 | B4: =((1+J4/100) * (1+L4/100) -1) * 100 -> 2.8192 | C4: 14.9 | D4: 9.7 | E4: -0.12 | F4: 1.4 | G4: =((1+K4/100) * (1+L4/100) -1) * 100 -> 4.5396 | H4: 2.6 | I4: 1.6 | J4: 1.6 | K4: 3.3 | L4: 1.2

Sheet Prev_j_2016
A1: time | B1: PIB_variation | C1: taux_epargne | D1: chomage | E1: EURIBOR | F1: Taux_long | G1: FBCF_variation | H1: RDB_variation | I1: salaires_brut | J1: N_PIB_réel | K1: N_FBCF_réel | L1: N_Déflateur
A2: 2016 | B2: =((1+J2/100) * (1+L2/100) -1) * 100 -> 2.5154 | C2: 14.3 | D2: 10.1 | E2: -0.3 | F2: 0.6 | G2: =((1+K2/100) * (1+L2/100) -1) * 100 -> 4.5374 | H2: 2.1 | I2: 1.2 | J2: 1.4 | K2: 3.4 | L2: 1.1
A3: 2017 | B3: =((1+J3/100) * (1+L3/100) -1) * 100 -> 2.6165 | C3: 14.4 | D3: 10 | E3: -0.3 | F3: 0.7 | G3: =((1+K3/100) * (1+L3/100) -1) * 100 -> 4.2341 | H3: 2.3 | I3: 1.3 | J3: 1.5 | K3: 3.1 | L3: 1.1
A4: 2018 | B4: =((1+J4/100) * (1+L4/100) -1) * 100 -> 2.9208 | C4: 14.6 | D4: 9.8 | E4: -0.3 | F4: 1 | G4: =((1+K4/100) * (1+L4/100) -1) * 100 -> 4.6429 | H4: 2.9 | I4: 1.6 | J4: 1.6 | K4: 3.3 | L4: 1.3

Sheet Prev_d_2016
A1: time | B1: PIB_variation | C1: taux_epargne | D1: chomage | E1: EURIBOR | F1: Taux_long | G1: FBCF_variation | H1: RDB_variation | I1: salaires_brut | J1: N_PIB_réel | K1: N_FBCF_réel | L1: N_Déflateur
A2: 2016 | B2: =((1+J2/100) * (1+L2/100) -1) * 100 -> 2.1104 | C2: 14.8 | D2: 10 | E2: -0.3 | F2: 0.5 | G2: =((1+K2/100) * (1+L2/100) -1) * 100 -> 4.1264 | H2: 1.8 | I2: 1.2 | J2: 1.3 | K2: 3.3 | L2: 0.8
A3: 2017 | B3: =((1+J3/100) * (1+L3/100) -1) * 100 -> 2.2117 | C3: 14.7 | D3: 9.9 | E3: -0.3 | F3: 0.9 | G3: =((1+K3/100) * (1+L3/100) -1) * 100 -> 2.7162 | H3: 2 | I3: 1.4 | J3: 1.3 | K3: 1.8 | L3: 0.9
A4: 2018 | B4: =((1+J4/100) * (1+L4/100) -1) * 100 -> 2.6168 | C4: 14.5 | D4: 9.7 | E4: -0.2 | F4: 1.1 | G4: =((1+K4/100) * (1+L4/100) -1) * 100 -> 3.6288 | H4: 2.5 | I4: 1.6 | J4: 1.4 | K4: 2.4 | L4: 1.2

Sheet Prev_j_2017
A1: time | B1: PIB_variation | C1: taux_epargne | D1: chomage | E1: EURIBOR | F1: Taux_long | G1: FBCF_variation | H1: RDB_variation | I1: salaires | J1: N_PIB_réel | K1: N_FBCF_réel | L1: N_Déflateur
A2: 2017 | B2: =((1+J2/100) * (1+Prev_d_2016!L2/100) -1) * 100 -> 2.2112 | C2: 14.8 | D2: 9.7 | E2: -0.3 | F2: 0.9 | G2: =((1+K2/100) * (1+L2/100) -1) * 100 -> 3.5234 | H2: 2.1 | I2: 1.5 | J2: 1.4 | K2: 2.6 | L2: 0.9
A3: 2018 | B3: =((1+J3/100) * (1+Prev_d_2016!L3/100) -1) * 100 -> 2.5144 | C3: 14.7 | D3: 9.6 | E3: -0.2 | F3: 1.2 | G3: =((1+K3/100) * (1+L3/100) -1) * 100 -> 3.6275 | H3: 2.6 | I3: 1.6 | J3: 1.6 | K3: 2.5 | L3: 1.1
A4: 2019 | B4: =((1+J4/100) * (1+Prev_d_2016!L4/100) -1) * 100 -> 2.8192 | C4: 14.5 | D4: 9.3 | E4: 0 | F4: 1.5 | G4: =((1+K4/100) * (1+L4/100) -1) * 100 -> 3.9338 | H4: 2.9 | I4: 1.7 | J4: 1.6 | K4: 2.6 | L4: 1.3

Sheet Prev_d_2017
A1: time | B1: PIB_variation | C1: taux_epargne | D1: chomage | E1: EURIBOR | F1: Taux_long | G1: FBCF_variation | H1: RDB_variation | I1: salaires_brut | J1: N_PIB_réel | K1: N_FBCF_réel | L1: N_Déflateur
A2: 2017 | B2: =((1+J2/100) * (1+Prev_d_2016!L2/100) -1) * 100 -> 2.6144 | C2: 14.8 | D2: 9.6 | E2: -0.3 | F2: 0.8 | G2: =((1+K2/100) * (1+L2/100) -1) * 100 -> 4.7246 | H2: 2.5 | I2: 2 | J2: 1.8 | K2: 4.1 | L2: 0.6
A3: 2018 | B3: =((1+J3/100) * (1+Prev_d_2016!L3/100) -1) * 100 -> 2.6153 | C3: 14.7 | D3: 9.6 | E3: -0.3 | F3: 0.7 | G3: =((1+K3/100) * (1+L3/100) -1) * 100 -> 3.927 | H3: 2.9 | I3: 1.6 | J3: 1.7 | K3: 3 | L3: 0.9
A4: 2019 | B4: =((1+J4/100) * (1+Prev_d_2016!L4/100) -1) * 100 -> 3.0216 | C4: 14.5 | D4: 9.2 | E4: -0.1 | F4: 1 | G4: =((1+K4/100) * (1+L4/100) -1) * 100 -> 4.1364 | H4: 3.5 | I4: 1.7 | J4: 1.8 | K4: 2.8 | L4: 1.3
H27: =1.017 *1.003 -1 -> 0.020051

Sheet Prev_j_2018
A1: time | B1: PIB_variation | C1: taux_epargne | D1: chomage | E1: EURIBOR | F1: Taux_long | G1: FBCF_variation | H1: RDB_variation | I1: salaires_brut | J1: N_PIB_réel | K1: N_FBCF_réel | L1: N_Déflateur
A2: 2018 | B2: =((1+J2/100) * (1+Prev_d_2016!L2/100) -1) * 100 -> 2.6144 | C2: NA | D2: 9.1 | E2: -0.3 | F2: 0.9 | G2: =((1+K2/100) * (1+L2/100) -1) * 100 -> 4.5324 | H2: NA | I2: NA | J2: 1.8 | K2: 3.6 | L2: 0.9
A3: 2019 | B3: =((1+J3/100) * (1+Prev_d_2016!L3/100) -1) * 100 -> 2.6153 | C3: NA | D3: 8.8 | E3: -0.2 | F3: 1.1 | G3: =((1+K3/100) * (1+L3/100) -1) * 100 -> 4.3406 | H3: NA | I3: NA | J3: 1.7 | K3: 2.9 | L3: 1.4
A4: 2020 | B4: =((1+J4/100) * (1+Prev_d_2016!L4/100) -1) * 100 -> 2.8192 | C4: NA | D4: 8.3 | E4: 0.2 | F4: 1.3 | G4: =((1+K4/100) * (1+L4/100) -1) * 100 -> 4.14 | H4: NA | I4: NA | J4: 1.6 | K4: 2.5 | L4: 1.6
A8: Problème : Manque de données

Sheet Prev_d_2018
A1: time | B1: PIB_variation | C1: taux_epargne | D1: chomage | E1: EURIBOR | F1: Taux_long | G1: FBCF_variation | H1: RDB_variation | I1: salaires_brut | J1: N_PIB_réel | K1: N_FBCF_réel | L1: N_Déflateur
A2: 2018 | B2: =((1+J2/100) * (1+Prev_d_2016!L2/100) -1) * 100 -> 2.312 | C2: 14.6 | D2: 9.1 | E2: -0.3 | F2: 0.8 | G2: =((1+K2/100) * (1+L2/100) -1) * 100 -> 4.939 | H2: 3.1 | I2: 1.9 | J2: 1.5 | K2: 3.9 | L2: 1
A3: 2019 | B3: =((1+J3/100) * (1+Prev_d_2016!L3/100) -1) * 100 -> 2.4135 | C3: 14.9 | D3: 8.9 | E3: -0.3 | F3: 0.9 | G3: =((1+K3/100) * (1+L3/100) -1) * 100 -> 5.6559 | H3: 3.2 | I3: 2.3 | J3: 1.5 | K3: 4.3 | L3: 1.3
A4: 2020 | B4: =((1+J4/100) * (1+Prev_d_2016!L4/100) -1) * 100 -> 2.8192 | C4: 14.9 | D4: 8.5 | E4: 0 | F4: 1.2 | G4: =((1+K4/100) * (1+L4/100) -1) * 100 -> 4.4435 | H4: 2.9 | I4: 2.4 | J4: 1.6 | K4: 2.9 | L4: 1.5

Sheet Prev_j_2019
A1: time | B1: PIB_variation | C1: taux_epargne | D1: chomage | E1: EURIBOR | F1: Taux_long | G1: FBCF_variation | H1: RDB_variation | I1: salaires_brut | J1: N_PIB_réel | K1: N_FBCF_réel | L1: N_Déflateur
A2: 2019 | B2: =((1+J2/100) * (1+Prev_d_2016!L2/100) -1) * 100 -> 2.1104 | C2: 15.3 | D2: 8.6 | E2: -0.3 | F2: 0.4 | G2: =((1+K2/100) * (1+L2/100) -1) * 100 -> 4.0351 | H2: NA | I2: 2.4 | J2: 1.3 | K2: 2.7 | L2: 1.3
A3: 2020 | B3: =((1+J3/100) * (1+Prev_d_2016!L3/100) -1) * 100 -> 2.3126 | C3: 15.2 | D3: 8.3 | E3: -0.3 | F3: 0.5 | G3: =((1+K3/100) * (1+L3/100) -1) * 100 -> 3.6288 | H3: NA | I3: 2.3 | J3: 1.4 | K3: 2.4 | L3: 1.2
A4: 2021 | B4: =((1+J4/100) * (1+Prev_d_2016!L4/100) -1) * 100 -> 2.6168 | C4: 15.1 | D4: 8.1 | E4: -0.2 | F4: 0.7 | G4: =((1+K4/100) * (1+L4/100) -1) * 100 -> 3.3252 | H4: NA | I4: 2.6 | J4: 1.4 | K4: 2.1 | L4: 1.2

Sheet Prev_d_2019
A1: time | B1: PIB_variation | C1: taux_epargne | D1: chomage | E1: EURIBOR | F1: Taux_long | G1: FBCF_variation | H1: RDB_variation | I1: salaires_brut | J1: N_PIB_réel | K1: N_FBCF_réel | L1: N_Déflateur
A2: 2019 | B2: =((1+J2/100) * (1+Prev_d_2016!L2/100) -1) * 100 -> 2.1104 | C2: 14.9 | D2: 8.5 | E2: -0.4 | F2: 0.1 | G2: =((1+K2/100) * (1+L2/100) -1) * 100 -> 5.4585 | H2: NA | I2: 1.9 | J2: 1.3 | K2: 3.9 | L2: 1.5
A3: 2020 | B3: =((1+J3/100) * (1+Prev_d_2016!L3/100) -1) * 100 -> 2.0099 | C3: 15 | D3: 8.2 | E3: -0.4 | F3: 0.1 | G3: =((1+K3/100) * (1+L3/100) -1) * 100 -> 3.9248 | H3: NA | I3: 1.8 | J3: 1.1 | K3: 3.1 | L3: 0.8
A4: 2021 | B4: =((1+J4/100) * (1+Prev_d_2016!L4/100) -1) * 100 -> 2.5156 | C4: 14.8 | D4: 8.1 | E4: -0.4 | F4: 0.2 | G4: =((1+K4/100) * (1+L4/100) -1) * 100 -> 3.0189 | H4: NA | I4: 2.2 | J4: 1.3 | K4: 2.1 | L4: 0.9

Sheet Prev_j_2020
A1: time | B1: PIB_variation | C1: taux_epargne | D1: chomage | E1: EURIBOR | F1: Taux_long | G1: FBCF_variation | H1: RDB_variation | I1: salaires_brut | J1: N_PIB_réel | K1: N_FBCF_réel | L1: N_Déflateur
A2: 2020 | B2: =((1+J2/100) * (1+Prev_d_2016!L2/100) -1) * 100 -> -9.5824 | C2: 22.3 | D2: 10.1 | E2: -0.4 | F2: 0 | G2: =((1+K2/100) * (1+L2/100) -1) * 100 -> -22.4563 | H2: NA | I2: -2.7 | J2: -10.3 | K2: -23.3 | L2: 1.1
A3: 2021 | B3: =((1+J3/100) * (1+Prev_d_2016!L3/100) -1) * 100 -> 7.8621 | C3: 16.6 | D3: 11.7 | E3: -0.4 | F3: 0.2 | G3: =((1+K3/100) * (1+L3/100) -1) * 100 -> 17.2826 | H3: NA | I3: 3 | J3: 6.9 | K3: 17.4 | L3: -0.1
A4: 2022 | B4: =((1+J4/100) * (1+Prev_d_2016!L4/100) -1) * 100 -> 5.1468 | C4: 14.8 | D4: 10.4 | E4: -0.4 | F4: 0.3 | G4: =((1+K4/100) * (1+L4/100) -1) * 100 -> 9.0344 | H4: NA | I4: 0.5 | J4: 3.9 | K4: 8.6 | L4: 0.4

Sheet Prev_d_2020
A1: time | B1: PIB_variation | C1: taux_epargne | D1: chomage | E1: EURIBOR | F1: Taux_long | G1: FBCF_variation | H1: RDB_variation | I1: salaires_brut | J1: N_PIB_réel | K1: N_FBCF_réel | L1: N_Déflateur
A2: 2020 | B2: =((1+J2/100) * (1+Prev_d_2016!L2/100) -1) * 100 -> -8.5744 | C2: 22.2 | D2: 8.5 | E2: -0.4 | F2: -0.1 | G2: =((1+K2/100) * (1+L2/100) -1) * 100 -> -7.894 | H2: NA | I2: -6.4 | J2: -9.3 | K2: -9.7 | L2: 2
A3: 2021 | B3: =((1+J3/100) * (1+Prev_d_2016!L3/100) -1) * 100 -> 5.7432 | C3: 19.5 | D3: 10.7 | E3: -0.5 | F3: -0.3 | G3: =((1+K3/100) * (1+L3/100) -1) * 100 -> 5.4274 | H3: NA | I3: 6.3 | J3: 4.8 | K3: 6.6 | L3: -1.1
A4: 2022 | B4: =((1+J4/100) * (1+Prev_d_2016!L4/100) -1) * 100 -> 6.26 | C4: 14.5 | D4: 9.5 | E4: -0.5 | F4: -0.2 | G4: =((1+K4/100) * (1+L4/100) -1) * 100 -> 5.3196 | H4: NA | I4: 2.6 | J4: 5 | K4: 4.9 | L4: 0.4

Sheet Prev_j_2021
A1: time | B1: PIB_variation | C1: taux_epargne | D1: chomage | E1: EURIBOR | F1: Taux_long | G1: FBCF_variation | H1: RDB_variation | I1: salaires_brut | J1: N_PIB_réel | K1: N_FBCF_réel | L1: N_Déflateur
A2: 2021 | B2: =((1+J2/100) * (1+Prev_d_2016!L2/100) -1) * 100 -> 6.6464 | C2: 19.3 | D2: 8.7 | E2: -0.5 | F2: 0.1 | G2: =((1+K2/100) * (1+L2/100) -1) * 100 -> 9.0418 | H2: NA | I2: 4.8 | J2: 5.8 | K2: 9.7 | L2: -0.6
A3: 2022 | B3: =((1+J3/100) * (1+Prev_d_2016!L3/100) -1) * 100 -> 5.0369 | C3: 14.6 | D3: 9.2 | E3: -0.5 | F3: 0.4 | G3: =((1+K3/100) * (1+L3/100) -1) * 100 -> 4.6408 | H3: NA | I3: 4.2 | J3: 4.1 | K3: 3.4 | L3: 1.2
A4: 2023 | B4: =((1+J4/100) * (1+Prev_d_2016!L4/100) -1) * 100 -> 3.3252 | C4: 14.1 | D4: 8.9 | E4: -0.3 | F4: 0.6 | G4: =((1+K4/100) * (1+L4/100) -1) * 100 -> 4.333 | H4: NA | I4: 2.7 | J4: 2.1 | K4: 3.3 | L4: 1

Sheet Prev_d_2021
A1: time | B1: PIB_variation | C1: taux_epargne | D1: chomage | E1: EURIBOR | F1: Taux_long | G1: FBCF_variation | H1: RDB_variation | I1: salaires_brut | J1: N_PIB_réel | K1: N_FBCF_réel | L1: N_Déflateur
A2: 2021 | B2: =((1+J2/100) * (1+Prev_d_2016!L2/100) -1) * 100 -> 7.5536 | C2: 19.3 | D2: 8 | E2: -0.5 | F2: 0 | G2: =((1+K2/100) * (1+L2/100) -1) * 100 -> 12.5936 | H2: NA | I2: 6.4 | J2: 6.7 | K2: 11.7 | L2: 0.8
A3: 2022 | B3: =((1+J3/100) * (1+Prev_d_2016!L3/100) -1) * 100 -> 4.5324 | C3: 15.1 | D3: 7.9 | E3: -0.5 | F3: 0.1 | G3: =((1+K3/100) * (1+L3/100) -1) * 100 -> 2.912 | H3: NA | I3: 6.1 | J3: 3.6 | K3: 2.4 | L3: 0.5
A4: 2023 | B4: =((1+J4/100) * (1+Prev_d_2016!L4/100) -1) * 100 -> 3.4264 | C4: 14.6 | D4: 7.8 | E4: -0.2 | F4: 0.2 | G4: =((1+K4/100) * (1+L4/100) -1) * 100 -> 6.1748 | H4: NA | I4: 3.2 | J4: 2.2 | K4: 4.4 | L4: 1.7

Sheet Prev_j_2022
A1: time | B1: PIB_variation | C1: taux_epargne | D1: chomage | E1: EURIBOR | F1: Taux_long | G1: FBCF_variation | H1: RDB_variation | I1: salaires_brut | J1: N_PIB_réel | K1: N_FBCF_réel | L1: N_Déflateur
A2: 2022 | B2: =((1+J2/100) * (1+Prev_d_2016!L2/100) -1) * 100 -> 3.5216 | C2: 16.5 | D2: 7.4 | E2: 0 | F2: 1.3 | G2: =((1+K2/100) * (1+L2/100) -1) * 100 -> 3.6288 | H2: NA | I2: 4.9 | J2: 2.7 | K2: 1.2 | L2: 2.4
A3: 2023 | B3: =((1+J3/100) * (1+Prev_d_2016!L3/100) -1) * 100 -> 2.1108 | C3: 15.1 | D3: 7.7 | E3: 1.3 | F3: 1.8 | G3: =((1+K3/100) * (1+L3/100) -1) * 100 -> 5.6768 | H3: NA | I3: 5 | J3: 1.2 | K3: 2.4 | L3: 3.2
A4: 2024 | B4: =((1+J4/100) * (1+Prev_d_2016!L4/100) -1) * 100 -> 2.9204 | C4: 14.9 | D4: 7.9 | E4: 1.6 | F4: 1.9 | G4: =((1+K4/100) * (1+L4/100) -1) * 100 -> 5.4665 | H4: NA | I4: 3.6 | J4: 1.7 | K4: 3.5 | L4: 1.9

Sheet Prev_d_2022
A1: time | B1: PIB_variation | C1: taux_epargne | D1: chomage | E1: EURIBOR | F1: Taux_long | G1: FBCF_variation | H1: RDB_variation | I1: salaires_brut | J1: N_PIB_réel | K1: N_FBCF_réel | L1: N_Déflateur
A2: 2022 | B2: =((1+J2/100) * (1+Prev_d_2016!L2/100) -1) * 100 -> 3.4208 | C2: 16.5 | D2: 7.3 | E2: 0.4 | F2: 1.7 | G2: =((1+K2/100) * (1+L2/100) -1) * 100 -> 5.678 | H2: NA | I2: 3.8 | J2: 2.6 | K2: 3 | L2: 2.6
A3: 2023 | B3: =((1+J3/100) * (1+Prev_d_2016!L3/100) -1) * 100 -> 1.2027 | C3: 16.1 | D3: 7.5 | E3: 2.9 | F3: 2.5 | G3: =((1+K3/100) * (1+L3/100) -1) * 100 -> 5.9738 | H3: NA | I3: 6.2 | J3: 0.3 | K3: 1.8 | L3: 4.1
A4: 2024 | B4: =((1+J4/100) * (1+Prev_d_2016!L4/100) -1) * 100 -> 2.4144 | C4: 16.5 | D4: 8.2 | E4: 2.7 | F4: 2.5 | G4: =((1+K4/100) * (1+L4/100) -1) * 100 -> 4.236 | H4: NA | I4: 4.7 | J4: 1.2 | K4: 1.2 | L4: 3

Sheet Prev_j_2023
A1: time | B1: PIB_variation | C1: taux_epargne | D1: chomage | E1: EURIBOR | F1: Taux_long | G1: FBCF_variation | H1: RDB_variation | I1: salaires_brut | J1: N_PIB_réel | K1: N_FBCF_réel | L1: N_Déflateur
A2: 2023 | B2: =((1+J2/100) * (1+Prev_d_2016!L2/100) -1) * 100 -> 1.5056 | C2: 16.6 | D2: 7.1 | E2: 3.4 | F2: 3 | G2: =((1+K2/100) * (1+L2/100) -1) * 100 -> 6.59 | H2: NA | I2: 5.5 | J2: 0.7 | K2: 2 | L2: 4.5
A3: 2024 | B3: =((1+J3/100) * (1+Prev_d_2016!L3/100) -1) * 100 -> 1.909 | C3: 16.3 | D3: 7.5 | E3: 3.4 | F3: 3.1 | G3: =((1+K3/100) * (1+L3/100) -1) * 100 -> 3.113 | H3: NA | I3: 4.2 | J3: 1 | K3: 0.5 | L3: 2.6
A4: 2025 | B4: =((1+J4/100) * (1+Prev_d_2016!L4/100) -1) * 100 -> 2.718 | C4: 15.6 | D4: 7.6 | E4: 2.9 | F4: 3.2 | G4: =((1+K4/100) * (1+L4/100) -1) * 100 -> 3.734 | H4: NA | I4: 3.6 | J4: 1.5 | K4: 1.7 | L4: 2

Sheet Prev_d_2023
A1: time | B1: PIB_variation | C1: taux_epargne | D1: chomage | E1: EURIBOR | F1: Taux_long | G1: FBCF_variation | H1: RDB_variation | I1: salaires_brut | J1: N_PIB_réel | K1: N_FBCF_réel | L1: N_Déflateur
A2: 2023 | B2: =((1+J2/100) * (1+Prev_d_2016!L2/100) -1) * 100 -> 1.7072 | C2: 17.7 | D2: 7.3 | E2: 3.4 | F2: 3 | G2: =((1+K2/100) * (1+L2/100) -1) * 100 -> 9.6173 | H2: NA | I2: 5 | J2: 0.9 | K2: 4.1 | L2: 5.3
A3: 2024 | B3: =((1+J3/100) * (1+Prev_d_2016!L3/100) -1) * 100 -> 1.8081 | C3: 17.3 | D3: 7.6 | E3: 3.6 | F3: 3.2 | G3: =((1+K3/100) * (1+L3/100) -1) * 100 -> 3.113 | H3: NA | I3: 4.1 | J3: 0.9 | K3: 0.5 | L3: 2.6
A4: 2025 | B4: =((1+J4/100) * (1+Prev_d_2016!L4/100) -1) * 100 -> 2.5156 | C4: 16.7 | D4: 7.8 | E4: 2.8 | F4: 3.3 | G4: =((1+K4/100) * (1+L4/100) -1) * 100 -> 3.224 | H4: NA | I4: 3.2 | J4: 1.3 | K4: 1.2 | L4: 2

Sheet Prev_j_2024
A1: time | B1: PIB_variation | C1: taux_epargne | D1: chomage | E1: EURIBOR | F1: Taux_long | G1: FBCF_variation | H1: RDB_variation | I1: salaires_brut | J1: N_PIB_réel | K1: N_FBCF_réel | L1: N_Déflateur
A2: 2024 | B2: =((1+J2/100) * (1+Prev_d_2016!L2/100) -1) * 100 -> 1.6064 | C2: 17.6 | D2: 7.5 | E2: 3.6 | F2: 2.9 | G2: =((1+K2/100) * (1+L2/100) -1) * 100 -> 3.5174 | H2: NA | I2: 3.1 | J2: 0.8 | K2: 0.6 | L2: 2.9
A3: 2025 | B3: =((1+J3/100) * (1+Prev_d_2016!L3/100) -1) * 100 -> 2.1108 | C3: 16.9 | D3: 7.8 | E3: 2.8 | F3: 3 | G3: =((1+K3/100) * (1+L3/100) -1) * 100 -> 2.921 | H3: NA | I3: 3.2 | J3: 1.2 | K3: 1.4 | L3: 1.5
A4: 2026 | B4: =((1+J4/100) * (1+Prev_d_2016!L4/100) -1) * 100 -> 2.8192 | C4: 16.5 | D4: 7.7 | E4: 2.5 | F4: 3 | G4: =((1+K4/100) * (1+L4/100) -1) * 100 -> 4.0384 | H4: NA | I4: 3.3 | J4: 1.6 | K4: 2.4 | L4: 1.6

Sheet Prev_d_2024
A1: time | B1: PIB_variation | C1: taux_epargne | D1: chomage | E1: EURIBOR | F1: Taux_long | G1: FBCF_variation | H1: RDB_variation | I1: salaires_brut | J1: N_PIB_réel | K1: N_FBCF_réel | L1: N_Déflateur
A2: 2024 | B2: =((1+J2/100) * (1+Prev_d_2016!L2/100) -1) * 100 -> 1.9088 | C2: 18 | D2: 7.4 | E2: 3.6 | F2: 3 | G2: =((1+K2/100) * (1+L2/100) -1) * 100 -> 1.1675 | H2: NA | I2: 2.8 | J2: 1.1 | K2: -1.3 | L2: 2.5
A3: 2025 | B3: =((1+J3/100) * (1+Prev_d_2016!L3/100) -1) * 100 -> 1.8081 | C3: 17.6 | D3: 7.8 | E3: 2.1 | F3: 3.2 | G3: =((1+K3/100) * (1+L3/100) -1) * 100 -> 1.297 | H3: NA | I3: 2.8 | J3: 0.9 | K3: -0.2 | L3: 1.5
A4: 2026 | B4: =((1+J4/100) * (1+Prev_d_2016!L4/100) -1) * 100 -> 2.5156 | C4: 17 | D4: 7.8 | E4: 2 | F4: 3.3 | G4: =((1+K4/100) * (1+L4/100) -1) * 100 -> 3.7336 | H4: NA | I4: 2.8 | J4: 1.3 | K4: 2.1 | L4: 1.6

Sheet Prev_j_2025
A1: time | B1: PIB_variation | C1: taux_epargne | D1: chomage | E1: EURIBOR | F1: Taux_long | G1: FBCF_variation | H1: RDB_variation | I1: salaires_brut | J1: N_PIB_réel | K1: N_FBCF_réel | L1: N_Déflateur
A2: 2025 | B2: =((1+J2/100) * (1+Prev_d_2016!L2/100) -1) * 100 -> 1.4048 | C2: 18.1 | D2: 7.5 | E2: 2.1 | F2: 3.4 | G2: =((1+K2/100) * (1+L2/100) -1) * 100 -> 0.694 | H2: NA | I2: 2.3 | J2: 0.6 | K2: -0.5 | L2: 1.2
A3: 2026 | B3: =((1+J3/100) * (1+Prev_d_2016!L3/100) -1) * 100 -> 1.909 | C3: 17.4 | D3: 7.7 | E3: 1.9 | F3: 3.6 | G3: =((1+K3/100) * (1+L3/100) -1) * 100 -> 2.6168 | H3: NA | I3: 2.3 | J3: 1 | K3: 1.2 | L3: 1.4
A4: 2027 | B4: =((1+J4/100) * (1+Prev_d_2016!L4/100) -1) * 100 -> 2.4144 | C4: 16.8 | D4: 7.4 | E4: 2.2 | F4: 3.8 | G4: =((1+K4/100) * (1+L4/100) -1) * 100 -> 3.327 | H4: NA | I4: 2.3 | J4: 1.2 | K4: 1.8 | L4: 1.5

Sheet Prev_d_2025
A1: time | B1: PIB_variation | C1: taux_epargne | D1: chomage | E1: EURIBOR | F1: Taux_long | G1: FBCF_variation | H1: RDB_variation | I1: salaires_brut | J1: N_PIB_réel | K1: N_FBCF_réel | L1: N_Déflateur
A2: 2025 | B2: =((1+J2/100) * (1+Prev_d_2016!L2/100) -1) * 100 -> 1.6064 | C2: 18.5 | D2: 7.6 | E2: 2.2 | F2: 3.4 | G2: =((1+K2/100) * (1+L2/100) -1) * 100 -> 1.2011 | H2: NA | I2: 2.1 | J2: 0.8 | K2: 0.1 | L2: 1.1
A3: 2026 | B3: =((1+J3/100) * (1+Prev_d_2016!L3/100) -1) * 100 -> 1.909 | C3: 17.9 | D3: 7.8 | E3: 2 | F3: 3.5 | G3: =((1+K3/100) * (1+L3/100) -1) * 100 -> 2.6168 | H3: NA | I3: 2.1 | J3: 1 | K3: 1.2 | L3: 1.4
A4: 2027 | B4: =((1+J4/100) * (1+Prev_d_2016!L4/100) -1) * 100 -> 2.212 | C4: 17.5 | D4: 7.6 | E4: 2.1 | F4: 3.8 | G4: =((1+K4/100) * (1+L4/100) -1) * 100 -> 3.1228 | H4: NA | I4: 2.2 | J4: 1 | K4: 1.9 | L4: 1.2

Sheet Last
A1: time | B1: PIB_variation | C1: taux_epargne | D1: chomage | E1: EURIBOR | F1: Taux_long | G1: FBCF_variation | H1: RDB_variation | I1: salaires_brut | J1: N_PIB_réel | K1: N_FBCF_réel | L1: N_Déflateur
A2: 2026 | B2: =((1+J2/100) * (1+Prev_d_2016!L2/100) -1) * 100 -> 1.7072 | C2: NA | D2: 8 | E2: 2.3 | F2: 3.6 | G2: =((1+K2/100) * (1+L2/100) -1) * 100 -> 2.1098 | H2: NA | I2: NA | J2: 0.9 | K2: 0.7 | L2: 1.4
A3: 2027 | B3: =((1+J3/100) * (1+Prev_d_2016!L3/100) -1) * 100 -> 1.7072 | C3: NA | D3: 7.9 | E3: 2.6 | F3: 3.9 | G3: =((1+K3/100) * (1+L3/100) -1) * 100 -> 2.8195 | H3: NA | I3: NA | J3: 0.8 | K3: 1.5 | L3: 1.3
A4: 2028 | B4: =((1+J4/100) * (1+Prev_d_2016!L4/100) -1) * 100 -> 2.4144 | C4: NA | D4: 7.7 | E4: 2.6 | F4: 4.1 | G4: =((1+K4/100) * (1+L4/100) -1) * 100 -> 3.124 | H4: NA | I4: NA | J4: 1.2 | K4: 1.6 | L4: 1.5
